coopr.age-1.1.4-py2.7-nspkg.pth
coopr/age/__init__.py
coopr/age/CooprAge.py
coopr/age/CooprAgeCore.py
coopr/age/Editor.py
coopr/age/PyomoSyntax.py
coopr/age/UIProblem.py
coopr.age-1.1.4.dist-info/DESCRIPTION.rst
coopr.age-1.1.4.dist-info/entry_points.txt
coopr.age-1.1.4.dist-info/METADATA
coopr.age-1.1.4.dist-info/metadata.json
coopr.age-1.1.4.dist-info/namespace_packages.txt
coopr.age-1.1.4.dist-info/RECORD
coopr.age-1.1.4.dist-info/top_level.txt
coopr.age-1.1.4.dist-info/WHEEL
