Metadata-Version: 2.0
Name: coopr.age
Version: 1.1.4
Summary: A QT interface for Coopr that supports the formulation and analysis of Pyomo models
Home-page: https://software.sandia.gov/svn/public/coopr/coopr.age
Author: Carl Laird
Author-email: carl.laird@tamu.edu
License: BSD
Keywords: optimization
Platform: any
Classifier: Development Status :: 4 - Beta
Classifier: Intended Audience :: End Users/Desktop
Classifier: Intended Audience :: Science/Research
Classifier: License :: OSI Approved :: BSD License
Classifier: Natural Language :: English
Classifier: Operating System :: Microsoft :: Windows
Classifier: Operating System :: Unix
Classifier: Programming Language :: Python
Classifier: Programming Language :: Unix Shell
Classifier: Topic :: Scientific/Engineering :: Mathematics
Classifier: Topic :: Software Development :: Libraries :: Python Modules
Classifier: Topic :: Scientific/Engineering
